langchain_ibm_watsonxai/__init__.py
langchain_ibm_watsonxai/chat_models.py
langchain_ibm_watsonxai/llms.py
langchain_ibm_watsonxai-0.0.1.dist-info/LICENSE
langchain_ibm_watsonxai-0.0.1.dist-info/METADATA
langchain_ibm_watsonxai-0.0.1.dist-info/WHEEL
langchain_ibm_watsonxai-0.0.1.dist-info/RECORD
